{
    "point1": {
        "time": "03/13",
        "amount": "530ml",
        "reminder": "Please drink more water!"
    },
    "point2": {
        "time": "03/14",
        "amount": "780ml",
        "reminder": "Great effort!"
    },
    "point3": {
        "time": "03/15",
        "amount": "2300ml",
        "reminder": "You met your daily goal!"
    },
    "point4": {
        "time": "03/16",
        "amount": "1800ml",
        "reminder": "Good job!"
    },
    "point5": {
        "time": "03/17",
        "amount": "1500ml",
        "reminder": "Keep it up!"
    },
    "point6": {
        "time": "03/18",
        "amount": "1200ml",
        "reminder": "Almost there!"
    },
    "point7": {
        "time": "03/19",
        "amount": "890ml",
        "reminder": "You can do better!"
    },
    "point8": {
        "time": "03/20",
        "amount": "2000ml",
        "reminder": "You met your daily goal!"
    },
    "point9": {
        "time": "03/21",
        "amount": "1600ml",
        "reminder": "Good job!"
    },
    "point10": {
        "time": "03/22",
        "amount": "1400ml",
        "reminder": "Keep it up!"
    }
}